{"pub": "chinadaily", "url": "https://global.chinadaily.com.cn/a/201910/25/WS5db2693ca310cf3e355739e3.html", "downloaded_at": "2019-10-25 03:30:14.989776+00:00", "title": "Inner Mongolia welcomes a golden harvest", "language": "en", "text": "A machine harvests rice in a field in October in the Daur Autonomous Banner of Morin Dawa of North China's Inner Mongolia autonomous region. [Photo by Jiang Xiwu for chinadaily.com.cn]\n\nAs the rice and corn grow ripe in October, the Daur Autonomous Banner of Morin Dawa in North China's Inner Mongolia autonomous region welcomes the golden harvest.\n\nThe region is known as an important production base for commodity grain and agricultural products. Corn, rice and soybeans are the region's three flagship agricultural products.", "description": "As the rice and corn grow ripe in October, the Daur Autonomous Banner of Morin Dawa in North China's Inner Mongolia autonomous region welcomes the golden harvest.", "authors": [], "top_image": "https://img2.chinadaily.com.cn/images/201910/25/5db2693ca310cf3e97a2f0dd.jpeg", "published_at": "2019-10-25"}