{"pub": "businessinsider", "url": "https://businessinsider.sg/singapore-among-the-worlds-10-most-expensive-countries-to-buy-starbucks-report-finds", "downloaded_at": "2019-09-30 11:31:56.463677+00:00", "title": "Singapore among the world\u2019s 10 most expensive countries to buy Starbucks, report finds", "language": "en", "text": "The price of a tall latte here was over 5 per cent more expensive than the global average, after accounting for purchasing power. The Straits Times\n\nMillennials, read this and weep: Singapore is among the 10 countries in the world where a Starbucks drink costs the most, according to a report published on Friday (Sep 27) by Australian personal finance website Finder.\n\nThe site compared the cost of a tall latte \u2013 converted to US dollars \u2013 in 76 countries around the world and used it to create a \u201cStarbucks Index\u201d ranking the prices.\n\nSingapore came in eighth on the list, with a tall latte at S$4.50 (S$6.20).\n\nDespite the name, a tall latte (350ml) in Starbucks lingo is considered a small-sized drink, with bigger options dubbed \u201cGrande\u201d and \u201cVenti\u201d.\n\nUnder Finder\u2019s ranking, the city with the priciest tall latte was Copenhagen (US$6.05), followed by Arau (Switzerland), Vantaa (Finland), Macau, and Luxembourg.\n\nOn home turf in New York, the drink cost US$4.30, while Malaysia\u2019s Selangor came in 54th at US$3.04 (RM12.70).\n\nThe priciest spots in Asia to get Starbucks were Macau (US$5.21), Hong Kong (US$4.60), and Singapore (S$4.50). Finder\n\nMeanwhile the cheapest place in the world to get Starbucks is Turkey, with a tall latte coming in at a steal of US$1.78 a cup. The next cheapest places were Egypt, Colombia, Argentina and Mexico.\n\nThe cheapest place to get Starbucks in Asia was the Philippines\u2019 Quezon City, at (US$2.69) a cup. Finder\n\nTo account for the difference in consumer purchasing power between countries, Finder plotted the GDP-per-capita for each country against the cost of a tall latte to create an average global trend line.\n\nAccording to the data, Singapore\u2019s pricing was over 5 per cent more expensive than the global average, after accounting for purchasing power, while Malaysia\u2019s was 6 per cent cheaper.\n\nFinder\n\nFinder admitted its index was an \u201cinformal way\u201d to compare Starbucks prices, and did not account for factors such as the cost of raw coffee, local labour costs, and Starbucks\u2019 pricing strategies.\n\nRead also:", "description": "Business Insider - The price of a tall latte here was over 5 per cent more expensive then the global average, after accounting for purchasing power.. Read more at businessinsider.sg", "authors": ["Rachel Genevieve Chia"], "top_image": "https://static.businessinsider.sg/sites/2/2019/09/file6ucd2gb5393u08ml9qc.jpg", "published_at": "2019-09-30"}