{"pub": "businessinsider", "url": "https://businessinsider.com/college-football-picks-week-3-2019-9", "downloaded_at": "2019-09-13 19:22:28.982592+00:00", "title": "Our 7 best bets for Week 3 of the college football season", "language": "en", "text": "Penn State was the only pick that came through for us last week, and we're riding them again this Saturday as they welcome Pittsburgh to State College.\n\nThis is the 100th meeting between these two schools, with the rivalry renewed in 2016 when Pittsburgh shocked Penn State with a 42-39 upset. Since then, the Nittany Lions have gone to great lengths to crush the Panthers whenever they see them, capped off by a 51-6 win last year.\n\nAfter a slow start against Buffalo last week, Penn State should be ready to go from the opening whistle for such an important rivalry game. This should not be close.", "description": "The UCF Knights play their biggest game of the year against Stanford this weekend \u2014 can they do enough to cover?", "authors": ["Tyler Lauletta"], "top_image": "https://amp.businessinsider.com/images/5d7bd9b52e22af1a93785a29-2560-1280.jpg", "published_at": "2019-09-13"}