{"pub": "zdnet", "url": "https://www.zdnet.com/article/rip-itunes-apple-releases-macos-10-15-catalina", "downloaded_at": "2019-10-07 20:03:32.209309+00:00", "title": "RIP iTunes: Apple releases MacOS 10.15 Catalina", "language": "en", "text": "Have Apple events lost their shine? ZDNet's Adrian Kingsley-Hughes sits down with Karen Roby to discuss if Apple events help sell iPhones, or are they a tool Apple uses to reassure investors and journalists? Read more: https://zd.net/2N9Xhoy\n\nApple on Monday announced MacOS 10.15 Catalina will be available today for support Macs The release follows the launch of iOS 13 and iPadOS in September.\n\nArguably, Catalina's biggest feature is that it signals the end of iTunes. Apple unbundled all of the various functionality of iTunes, such as Apple Music, Podcasts, and Apple TV. But don't worry, you can still sync your iPhone or iPad with your Mac -- that's done with the Finder app now.\n\nAccording to Apple, Catalina will run on the following Macs:\n\nMacBook 2015 or later\n\nMacBook Air 2012 or later\n\nMacBook Pro 2012 or later\n\nMac Mini 2012 or later\n\niMac 2012 or later\n\niMac Pro 2017 or later\n\nMac Pro 2013 or later\n\nOther features included in Catalina include Apple Arcade, the expansion of iPad apps being ported to Mac, and the ability to use an iPad as an external monitor with the Sidecar feature.\n\nApple also expanded its Screen Time feature to the Mac, giving you greater insight into your usage habits on all of your Apple devices. Screen Time also expands parental controls to the Mac for the first time.\n\nBefore you dive into system preferences and update, do some routine maintenance to ensure it's a smooth installation.", "description": "The latest version of MacOS gets rid of iTunes, and it's probably for the better.", "authors": ["Jason Cipriani"], "top_image": "https://zdnet3.cbsistatic.com/hub/i/r/2019/06/27/9db3f3ef-2826-4231-b8ac-24490cf0fc66/thumbnail/770x578/78a5b771a4891792fd005c90ef842ade/macos-catalina-music.jpg", "published_at": "2019-10-07"}